ledger_reader/__init__.py
ledger_reader/reader.py
ledger_reader/test_reader.py
ledger_reader-0.7.dist-info/LICENSE
ledger_reader-0.7.dist-info/METADATA
ledger_reader-0.7.dist-info/WHEEL
ledger_reader-0.7.dist-info/top_level.txt
ledger_reader-0.7.dist-info/RECORD
