Metadata-Version: 2.1
Name: ledger-reader
Version: 0.7
Summary: A simple parser for hledger journal files.
Home-page: https://github.com/rmcl/ledger_reader
Author: Russell McLoughlin
Author-email: russ.mcl@gmail.com
Classifier: Programming Language :: Python :: 3
Classifier: License :: OSI Approved :: MIT License
Classifier: Operating System :: OS Independent
Requires-Python: >=3.7
License-File: LICENSE
Requires-Dist: rply
